canvas/__init__.py
canvas/__main__.py
canvas/templates/rl/cookiecutter.json
canvas/templates/rl/hooks/post_gen_project.py
canvas/templates/rl/hooks/pre_gen_project.py
canvas/templates/rl/{{cookiecutter.project_name}}/.gitignore
canvas/templates/rl/{{cookiecutter.project_name}}/LICENSE
canvas/templates/rl/{{cookiecutter.project_name}}/Makefile
canvas/templates/rl/{{cookiecutter.project_name}}/README.md
canvas/templates/rl/{{cookiecutter.project_name}}/pyproject.toml
canvas/templates/rl/{{cookiecutter.project_name}}/requirements.txt
canvas/templates/rl/{{cookiecutter.project_name}}/uv.lock
canvas/templates/rl/{{cookiecutter.project_name}}/src/main.py
canvas/templates/rl/{{cookiecutter.project_name}}/src/agent/__init__.py
canvas/templates/rl/{{cookiecutter.project_name}}/src/agent/model.py
canvas/templates/rl/{{cookiecutter.project_name}}/src/agent/network.py
canvas/templates/rl/{{cookiecutter.project_name}}/src/algorithm/__init__.py
canvas/templates/rl/{{cookiecutter.project_name}}/src/algorithm/evaluator.py
canvas/templates/rl/{{cookiecutter.project_name}}/src/algorithm/trainer.py
canvas/templates/rl/{{cookiecutter.project_name}}/src/config/config.yaml
canvas/templates/rl/{{cookiecutter.project_name}}/src/data/__init__.py
canvas/templates/rl/{{cookiecutter.project_name}}/src/data/batch.py
canvas/templates/rl/{{cookiecutter.project_name}}/src/data/rollout_buffer.py
canvas/templates/rl/{{cookiecutter.project_name}}/src/environment/__init__.py
canvas/templates/rl/{{cookiecutter.project_name}}/src/environment/environment.py
canvas/templates/sl/cookiecutter.json
canvas/templates/sl/hooks/post_gen_project.py
canvas/templates/sl/hooks/pre_gen_project.py
canvas/templates/sl/{{cookiecutter.project_name}}/.gitignore
canvas/templates/sl/{{cookiecutter.project_name}}/LICENSE
canvas/templates/sl/{{cookiecutter.project_name}}/Makefile
canvas/templates/sl/{{cookiecutter.project_name}}/README.md
canvas/templates/sl/{{cookiecutter.project_name}}/pyproject.toml
canvas_template-0.3.1.dist-info/METADATA
canvas_template-0.3.1.dist-info/WHEEL
canvas_template-0.3.1.dist-info/entry_points.txt
canvas_template-0.3.1.dist-info/licenses/LICENSE
canvas_template-0.3.1.dist-info/RECORD
