Metadata-Version: 2.4
Name: canvas-template
Version: 0.3.1
Summary: A modular, best-practice pytorch template for all your deep learning projects.
Author-email: Akshay Raman <ar8692@nyu.edu>
License-Expression: MIT
License-File: LICENSE
Classifier: Intended Audience :: Developers
Classifier: Intended Audience :: Science/Research
Classifier: Operating System :: OS Independent
Classifier: Programming Language :: Python :: 3
Classifier: Topic :: Scientific/Engineering
Classifier: Topic :: Scientific/Engineering :: Artificial Intelligence
Requires-Python: >=3.11
Requires-Dist: click>=8.2.1
Requires-Dist: cookiecutter>=2.6.0
Requires-Dist: mkdocs>=1.6.1
Requires-Dist: sphinx>=8.2.3
